{"is_source_file": true, "format": "TypeScript (TSX/React)", "description": "This source file defines a Sidebar component for a React application using Next.js. It includes navigation items with active state highlighting and external links for documentation.", "external_files": ["next/link", "next/navigation"], "external_methods": ["usePathname"], "published": ["default (Sidebar)"], "classes": [], "methods": [{"name": "NavItem", "description": "A React component that renders a navigation link with active state styling based on current pathname."}, {"name": "Sidebar", "description": "Main React component that renders the sidebar with navigational links and external resources."}], "calls": ["usePathname ()", "Link (from next/link)"], "search-terms": ["Sidebar", "Navigation", "Next.js link", "usePathname", "React component", "TypeScript", "Navigation menu"], "state": 2, "file_id": 16, "knowledge_revision": 67, "git_revision": "edc3c941531aad52f70f79c12a6e2da2417561c0", "revision_history": [{"34": ""}, {"67": "edc3c941531aad52f70f79c12a6e2da2417561c0"}], "ctags": [], "hash": "bdb1d3504844e94b6760f63a2bf5491f", "format-version": 4, "code-base-name": "integration_frontend", "filename": "integration_frontend/src/components/Sidebar.tsx"}