{"is_source_file": true, "format": "TypeScript/TSX", "description": "This file defines the layout component for a Next.js application, setting global styles, metadata, and the structure of the app shell with imported components like Topbar and Sidebar.", "external_files": ["next", "./globals.css", "@/styles/connector.css", "@/components/Topbar", "@/components/Sidebar"], "external_methods": [], "published": ["metadata", "RootLayout"], "classes": [], "methods": [{"name": "RootLayout", "description": "React component that renders the main layout including header, sidebar, and main content area."}], "calls": ["React.createElement", "Topbar", "Sidebar"], "search-terms": ["Next.js layout", "TypeScript React component", "metadata definition", "Topbar", "Sidebar", "global styles", "app shell"], "state": 2, "file_id": 5, "knowledge_revision": 287, "git_revision": "11cef7e3a5390183ed074c7beabab7b45a72ba64", "revision_history": [{"20": "15cdd2d04778470f70551981f64bce6e227c1f0f"}, {"38": "15cdd2d04778470f70551981f64bce6e227c1f0f"}, {"59": "edc3c941531aad52f70f79c12a6e2da2417561c0"}, {"232": "11cef7e3a5390183ed074c7beabab7b45a72ba64"}, {"287": "11cef7e3a5390183ed074c7beabab7b45a72ba64"}], "ctags": [], "hash": "9a58eac771b833e56aa42ff9ee23e761", "format-version": 4, "code-base-name": "integration_frontend", "filename": "integration_frontend/src/app/layout.tsx"}